tabloo/__init__.py
tabloo/backend.py
tabloo/server.py
tabloo/tabloo.py
tabloo/tabloo_cli.py
tabloo/static/index.html
tabloo/static/index_standalone.html
tabloo/static/index_standalone_dev.html
tabloo/static/main.js
tabloo/static/main.js.LICENSE.txt
tabloo/static/main.js.map
tabloo/static/main_standalone.js
tabloo/static/main_standalone.js.LICENSE.txt
tabloo/static/main_standalone.js.map
tabloo/static/styles.css
tabloo-0.1.0.dist-info/LICENSE
tabloo-0.1.0.dist-info/METADATA
tabloo-0.1.0.dist-info/WHEEL
tabloo-0.1.0.dist-info/entry_points.txt
tabloo-0.1.0.dist-info/top_level.txt
tabloo-0.1.0.dist-info/RECORD
