Metadata-Version: 2.1
Name: tabloo
Version: 0.1.0
Summary: Minimalistic dashboard app for visualizing tabular data
Home-page: https://github.com/bluenote10/tabloo
Author: Fabian Keller
Author-email: pypi.20.fkeller@spamgourmet.com
License: MIT
Keywords: table,dataframe,visualization,plots,dashboard
Platform: UNKNOWN
Classifier: Development Status :: 3 - Alpha
Classifier: Intended Audience :: Information Technology
Classifier: Topic :: Scientific/Engineering :: Visualization
Classifier: License :: OSI Approved :: MIT License
Classifier: Programming Language :: Python :: 3.7
Classifier: Programming Language :: Python :: 3.8
Classifier: Programming Language :: Python :: 3.9
Classifier: Programming Language :: Python :: 3.10
Classifier: Operating System :: OS Independent
License-File: LICENSE
